odoo/addons/account_budget_template/README.rst
odoo/addons/account_budget_template/__init__.py
odoo/addons/account_budget_template/__manifest__.py
odoo/addons/account_budget_template/i18n/account_budget_template.pot
odoo/addons/account_budget_template/i18n/de.po
odoo/addons/account_budget_template/i18n/es.po
odoo/addons/account_budget_template/i18n/pt.po
odoo/addons/account_budget_template/models/__init__.py
odoo/addons/account_budget_template/models/crossovered_budget.py
odoo/addons/account_budget_template/models/crossovered_budget_template.py
odoo/addons/account_budget_template/models/res_config_settings.py
odoo/addons/account_budget_template/readme/CONTRIBUTORS.rst
odoo/addons/account_budget_template/readme/DESCRIPTION.rst
odoo/addons/account_budget_template/security/ir.model.access.csv
odoo/addons/account_budget_template/static/description/icon.png
odoo/addons/account_budget_template/static/description/index.html
odoo/addons/account_budget_template/tests/__init__.py
odoo/addons/account_budget_template/tests/test_account_budget_template.py
odoo/addons/account_budget_template/views/crossovered_budget_template_view.xml
odoo/addons/account_budget_template/views/crossovered_budget_view.xml
odoo/addons/account_budget_template/views/res_config_settings_view.xml
odoo12_addon_account_budget_template-12.0.1.1.0.dist-info/METADATA
odoo12_addon_account_budget_template-12.0.1.1.0.dist-info/WHEEL
odoo12_addon_account_budget_template-12.0.1.1.0.dist-info/top_level.txt
odoo12_addon_account_budget_template-12.0.1.1.0.dist-info/RECORD
