Metadata-Version: 2.1
Name: odoo12-addon-account-budget-template
Version: 12.0.1.1.0
Summary: Account Budget Template
Home-page: https://github.com/OCA/account-budgeting
Author: AvanzOSC, Odoo Community Association (OCA)
Author-email: support@odoo-community.org
License: AGPL-3
Platform: UNKNOWN
Classifier: Programming Language :: Python
Classifier: Framework :: Odoo
Classifier: License :: OSI Approved :: GNU Affero General Public License v3
Requires-Python: >=3.5
Requires-Dist: odoo12-addon-account-budget-oca
Requires-Dist: odoo (<12.1dev,>=12.0a)
